Metadata-Version: 1.0
Name: analyze-distributions
Version: 0.1
Summary: Gaussian and Binomial distributions
Home-page: UNKNOWN
Author: Soufiane NAITTOULAHYANE
Author-email: naittou.soufiane@gmail.com
License: UNKNOWN
Platform: UNKNOWN
